ucdp_mem-0.3.0.dist-info/METADATA
ucdp_mem-0.3.0.dist-info/WHEEL
ucdp_mem-0.3.0.dist-info/entry_points.txt
ucdp_mem-0.3.0.dist-info/licenses/LICENSE
ucdp_mem/__init__.py
ucdp_mem/mem.py
ucdp_mem/memtechconstraints.py
ucdp_mem/otp.py
ucdp_mem/ram.py
ucdp_mem/rom.py
ucdp_mem/segmentation.py
ucdp_mem/segmux.py
ucdp_mem/types.py
ucdp_mem/ucdp-templates/segmux.sv.mako
ucdp_mem/util.py
ucdp_mem/wordmasks.py
ucdp_mem-0.3.0.dist-info/RECORD
