Metadata-Version: 2.1
Name: ucdp-mem
Version: 0.3.0
Summary: Unified Chip Design Platform - Memories
Classifier: Programming Language :: Python :: 3
Classifier: Operating System :: OS Independent
Project-URL: Homepage, https://github.com/nbiotcloud/ucdp-mem
Project-URL: Documentation, https://ucdp-mem.readthedocs.io/en/stable/
Project-URL: Bug Tracker, https://github.com/nbiotcloud/ucdp-mem/issues
Requires-Python: <4.0,>=3.10.0
Requires-Dist: ucdp>=0.16.0
Requires-Dist: ucdp-addr>=1.4.0
Requires-Dist: ucdp-glbl>=1.2.0
Requires-Dist: defaultlist>=1.0.0
